weblm/__init__.py
weblm/_async_client.py
weblm/_client.py
weblm/_exceptions.py
weblm/_response.py
weblm/py.typed
weblm_python-1.0.0.dist-info/METADATA
weblm_python-1.0.0.dist-info/WHEEL
weblm_python-1.0.0.dist-info/licenses/LICENSE
weblm_python-1.0.0.dist-info/RECORD
