Metadata-Version: 2.4
Name: weblm-python
Version: 1.0.0
Summary: The official Python SDK for WebLM, providing HTML to Markdown conversion and web content extraction capabilities
Project-URL: Homepage, https://weblm.dev
Project-URL: Bug Tracker, https://github.com/WebLM/weblm-python/issues
Project-URL: Documentation, https://weblm.dev/api-documentation
Project-URL: Source, https://github.com/WebLM/weblm-python
Author-email: WebLM <support@weblm.dev>
License: MIT
License-File: LICENSE
Classifier: Intended Audience :: Developers
Classifier: License :: OSI Approved :: MIT License
Classifier: Operating System :: OS Independent
Classifier: Programming Language :: Python :: 3
Classifier: Programming Language :: Python :: 3.9
Classifier: Programming Language :: Python :: 3.10
Classifier: Programming Language :: Python :: 3.11
Classifier: Topic :: Internet :: WWW/HTTP
Classifier: Topic :: Software Development :: Libraries :: Python Modules
Requires-Python: >=3.9
Requires-Dist: aiohttp>=3.8.0
Requires-Dist: pydantic>=2.10.0
Requires-Dist: requests>=2.27.0
Provides-Extra: dev
Requires-Dist: black>=25.0.0; extra == 'dev'
Requires-Dist: isort>=6.0.0; extra == 'dev'
Requires-Dist: mypy>=1.10.0; extra == 'dev'
Requires-Dist: pytest-asyncio>=0.25.0; extra == 'dev'
Requires-Dist: pytest-cov>=6.0.0; extra == 'dev'
Requires-Dist: pytest>=8.0.0; extra == 'dev'
Requires-Dist: ruff>=0.11.0; extra == 'dev'
